tarnished/__init__.py
tarnished/checksum.py
tarnished/cli.py
tarnished/defaults.py
tarnished/py.typed
tarnished/models/Config.py
tarnished/models/State.py
tarnished/models/__init__.py
tarnished-0.2.1.dist-info/METADATA
tarnished-0.2.1.dist-info/WHEEL
tarnished-0.2.1.dist-info/entry_points.txt
tarnished-0.2.1.dist-info/RECORD
