Metadata-Version: 2.4
Name: tarnished
Version: 0.2.1
Summary: File state checkpoint tool - has your code tarnished?
Project-URL: Homepage, https://github.com/RasmusGodske/tarnished
Project-URL: Documentation, https://github.com/RasmusGodske/tarnished#readme
Project-URL: Repository, https://github.com/RasmusGodske/tarnished
Project-URL: Issues, https://github.com/RasmusGodske/tarnished/issues
Project-URL: Changelog, https://github.com/RasmusGodske/tarnished/releases
Author: Rasmus Godske
Maintainer: Rasmus Godske
License: MIT
Keywords: checkpoint,checksum,cli,development,file-state,verification
Classifier: Development Status :: 4 - Beta
Classifier: Environment :: Console
Classifier: Intended Audience :: Developers
Classifier: License :: OSI Approved :: MIT License
Classifier: Operating System :: OS Independent
Classifier: Programming Language :: Python :: 3
Classifier: Programming Language :: Python :: 3.11
Classifier: Programming Language :: Python :: 3.12
Classifier: Programming Language :: Python :: 3.13
Classifier: Topic :: Software Development :: Quality Assurance
Classifier: Topic :: Software Development :: Testing
Classifier: Topic :: Utilities
Classifier: Typing :: Typed
Requires-Python: >=3.11
Provides-Extra: dev
Requires-Dist: mypy>=1.0; extra == 'dev'
Requires-Dist: pytest>=7.0; extra == 'dev'
Requires-Dist: ruff>=0.1; extra == 'dev'
